in_layers/__init__.py
in_layers/core/__init__.py
in_layers/core/entries.py
in_layers/core/globals/__init__.py
in_layers/core/globals/features.py
in_layers/core/globals/libs.py
in_layers/core/globals/logging.py
in_layers/core/globals/services.py
in_layers/core/layers/__init__.py
in_layers/core/layers/features.py
in_layers/core/layers/services.py
in_layers/core/libs.py
in_layers/core/models/__init__.py
in_layers/core/models/backends.py
in_layers/core/models/libs.py
in_layers/core/models/protocols.py
in_layers/core/models/query.py
in_layers/core/models/services.py
in_layers/core/protocols.py
in_layers/core/utils.py
in_layers_core-0.4.16.dist-info/METADATA
in_layers_core-0.4.16.dist-info/WHEEL
in_layers_core-0.4.16.dist-info/RECORD
