Metadata-Version: 2.4
Name: in-layers-core
Version: 0.4.16
Summary: The Python port of Node in Layers Core.
License: GPLv3
Keywords: layers,python,in-layers,node,domains
Author: Mike Cornwell
Author-email: mike@mikecornwell.com
Requires-Python: >=3.13,<4.0
Classifier: License :: Other/Proprietary License
Classifier: Programming Language :: Python :: 3
Classifier: Programming Language :: Python :: 3.13
Classifier: Programming Language :: Python :: 3.14
Requires-Dist: httpx (>=0.28.1,<0.29.0)
Requires-Dist: pydantic (>=2.12.5,<3.0.0)
Requires-Dist: python-box (>=7,<9)
